birdbuddy/__init__.py
birdbuddy/birds.py
birdbuddy/client.py
birdbuddy/const.py
birdbuddy/exceptions.py
birdbuddy/feed.py
birdbuddy/feeder.py
birdbuddy/media.py
birdbuddy/sightings.py
birdbuddy/user.py
birdbuddy/queries/__init__.py
birdbuddy/queries/auth.py
birdbuddy/queries/birds.py
birdbuddy/queries/debug.py
birdbuddy/queries/feeder.py
birdbuddy/queries/me.py
tests/__init__.py
tests/conftest.py
tests/test_issue_40.py
pybirdbuddy-0.0.19.dist-info/METADATA
pybirdbuddy-0.0.19.dist-info/WHEEL
pybirdbuddy-0.0.19.dist-info/top_level.txt
pybirdbuddy-0.0.19.dist-info/RECORD
