Metadata-Version: 2.2
Name: pybirdbuddy
Version: 0.0.19
Summary: A library to query data about a Bird Buddy smart bird feeder
Home-page: https://github.com/jhansche/pybirdbuddy
Author: jhansche
Author-email: madcoder@gmail.com
Requires-Python: >=3.10
Requires-Dist: python-graphql-client
Requires-Dist: langcodes
Dynamic: author
Dynamic: author-email
Dynamic: description
Dynamic: description-content-type
Dynamic: home-page
Dynamic: requires-dist
Dynamic: requires-python
Dynamic: summary
